github_crawler/__init__.py
github_crawler/main.py
github_crawler/user_profile_main.py
github_crawler/user_repos_main.py
github_parser_pkg/__init__.py
github_parser_pkg/main.py
github_parser_pkg/user_profile.py
github_parser_pkg/user_repos.py
github_crawler-0.0.6.dist-info/LICENSE
github_crawler-0.0.6.dist-info/METADATA
github_crawler-0.0.6.dist-info/WHEEL
github_crawler-0.0.6.dist-info/entry_points.txt
github_crawler-0.0.6.dist-info/top_level.txt
github_crawler-0.0.6.dist-info/RECORD
