Metadata-Version: 2.1
Name: github-crawler
Version: 0.0.6
Summary: A web spider to crawl public github repositories
Home-page: https://github.com/karthikhosur/Github-Crawler
Author: Karthik Hosur
Author-email: karthikhosur15@gmail.com
License: UNKNOWN
Platform: UNKNOWN
Classifier: Programming Language :: Python :: 3
Classifier: License :: OSI Approved :: MIT License
Classifier: Operating System :: OS Independent
Requires-Python: >=3.6
Requires-Dist: beautifulsoup4 (==4.9.3)
Requires-Dist: requests (==2.25.1)
